{
"__comment": "Designed by Pitkes22 with BDcraft Cubik PRO 0.93 Beta - http://bdcraft.net",
"textures": {
    "particle": "blocks/rasberry1",
    "leaves_spruce2": "blocks/rasberry1",
    "rasberry2": "blocks/rasberry2",
    "rasberry3": "blocks/rasberry3"
},
"elements": [ 
{
    "from": [ -2.4, 0, -2.4 ],
    "to": [ -2.31875, 27.3, 27.5 ],
    "rotation": { "origin": [ -2.4, 0, -2.4 ], "axis": "y", "angle": 45 },
    "faces": {
        "west":  { "uv": [ 0, 0, 16, 16 ], "texture": "#leaves_spruce2" },
        "east":  { "uv": [ 16, 0, 0, 16 ], "texture": "#leaves_spruce2" }
    }
},
{
    "from": [ 18.4, 0, -2.4 ],
    "to": [ 18.4812, 27.3, 27.5 ],
    "rotation": { "origin": [ 18.4, 0, -2.4 ], "axis": "y", "angle": -45 },
    "faces": {
        "west":  { "uv": [ 0, 0, 16, 16 ], "texture": "#leaves_spruce2" },
        "east":  { "uv": [ 16, 0, 0, 16 ], "texture": "#leaves_spruce2" }
    }
},
{
    "from": [ -5.65, 9.66875, -2.4 ],
    "to": [ 22.3, 9.75, 22.95 ],
    "rotation": { "origin": [ -5.65, 9.75, -2.4 ], "axis": "x", "angle": 22.5 },
    "faces": {
        "down":  { "uv": [ 16, 0, 0, 16 ], "rotation": 180, "texture": "#rasberry3" },
        "up":    { "uv": [ 0, 0, 16, 16 ], "texture": "#rasberry3" }
    }
},
{
    "from": [ -6.95, 2.51875, -3.7 ],
    "to": [ 21, 2.6, 21.65 ],
    "rotation": { "origin": [ -6.95, 2.6, -3.7 ], "axis": "x", "angle": -22.5 },
    "faces": {
        "down":  { "uv": [ 16, 0, 0, 16 ], "rotation": 180, "texture": "#rasberry3" },
        "up":    { "uv": [ 0, 0, 16, 16 ], "texture": "#rasberry3" }
    }
},
{
    "from": [ -7.625, 17.4688, -5.66875 ],
    "to": [ 20.325, 17.55, 19.6813 ],
    "rotation": { "origin": [ -7.625, 17.55, -5.66875 ], "axis": "x", "angle": 22.5 },
    "faces": {
        "down":  { "uv": [ 16, 0, 0, 16 ], "rotation": 180, "texture": "#rasberry3" },
        "up":    { "uv": [ 0, 0, 16, 16 ], "texture": "#rasberry3" }
    }
},
{
    "from": [ -3.7, 10.9688, -5.65 ],
    "to": [ 24.25, 11.05, 19.7 ],
    "rotation": { "origin": [ -3.7, 11.05, -5.65 ], "axis": "z", "angle": -22.5 },
    "faces": {
        "down":  { "uv": [ 16, 0, 0, 16 ], "rotation": 180, "texture": "#rasberry3" },
        "up":    { "uv": [ 0, 0, 16, 16 ], "texture": "#rasberry3" }
    }
},
{
    "from": [ -5, 6.41875, -3.05 ],
    "to": [ 22.95, 6.5, 22.3 ],
    "rotation": { "origin": [ -5, 6.5, -3.05 ], "axis": "z", "angle": 22.5 },
    "faces": {
        "down":  { "uv": [ 16, 0, 0, 16 ], "rotation": 180, "texture": "#rasberry3" },
        "up":    { "uv": [ 0, 0, 16, 16 ], "texture": "#rasberry3" }
    }
},
{
    "from": [ -6.95, 15.5187, -4.35 ],
    "to": [ 21, 15.6, 21 ],
    "rotation": { "origin": [ -6.95, 15.6, -4.35 ], "axis": "z", "angle": -22.5 },
    "faces": {
        "down":  { "uv": [ 16, 0, 0, 16 ], "rotation": 180, "texture": "#rasberry3" },
        "up":    { "uv": [ 0, 0, 16, 16 ], "texture": "#rasberry3" }
    }
}
]
}